{
  "data": {
    "article": {},
    "attachments": {},
    "author_id": "1634143760690057216",
    "conversation_id": "2052437596438245439",
    "created_at": "2026-05-08T22:21:28.000Z",
    "edit_controls": {
      "editable_until": "2026-05-08T23:21:28.000Z",
      "edits_remaining": 5,
      "is_edit_eligible": false
    },
    "edit_history_tweet_ids": [
      "2052876565462356463"
    ],
    "entities": {
      "mentions": [
        {
          "end": 12,
          "id": "2036464410286600192",
          "start": 0,
          "username": "hanya138884"
        }
      ]
    },
    "geo": {},
    "id": "2052876565462356463",
    "in_reply_to_user_id": "2036464410286600192",
    "lang": "zh",
    "note_tweet": {
      "entities": {}
    },
    "possibly_sensitive": false,
    "public_metrics": {
      "bookmark_count": 0,
      "impression_count": 0,
      "like_count": 0,
      "quote_count": 0,
      "reply_count": 0,
      "retweet_count": 0
    },
    "referenced_tweets": [
      {
        "id": "2052635280197505368",
        "type": "replied_to"
      }
    ],
    "reply_settings": "everyone",
    "text": "@hanya138884 我好像对这些没有什么兴趣，不过我会试试的！"
  },
  "includes": {
    "tweets": [
      {
        "article": {},
        "attachments": {},
        "author_id": "1634143760690057216",
        "conversation_id": "2052437596438245439",
        "created_at": "2026-05-08T22:21:28.000Z",
        "edit_controls": {
          "editable_until": "2026-05-08T23:21:28.000Z",
          "edits_remaining": 5,
          "is_edit_eligible": false
        },
        "edit_history_tweet_ids": [
          "2052876565462356463"
        ],
        "entities": {
          "mentions": [
            {
              "end": 12,
              "id": "2036464410286600192",
              "start": 0,
              "username": "hanya138884"
            }
          ]
        },
        "geo": {},
        "id": "2052876565462356463",
        "in_reply_to_user_id": "2036464410286600192",
        "lang": "zh",
        "note_tweet": {
          "entities": {}
        },
        "possibly_sensitive": false,
        "public_metrics": {
          "bookmark_count": 0,
          "impression_count": 0,
          "like_count": 0,
          "quote_count": 0,
          "reply_count": 0,
          "retweet_count": 0
        },
        "referenced_tweets": [
          {
            "id": "2052635280197505368",
            "type": "replied_to"
          }
        ],
        "reply_settings": "everyone",
        "text": "@hanya138884 我好像对这些没有什么兴趣，不过我会试试的！"
      },
      {
        "article": {},
        "attachments": {},
        "author_id": "2036464410286600192",
        "conversation_id": "2052437596438245439",
        "created_at": "2026-05-08T06:22:41.000Z",
        "edit_controls": {
          "editable_until": "2026-05-08T07:22:41.000Z",
          "edits_remaining": 5,
          "is_edit_eligible": false
        },
        "edit_history_tweet_ids": [
          "2052635280197505368"
        ],
        "entities": {
          "mentions": [
            {
              "end": 14,
              "id": "1634143760690057216",
              "start": 0,
              "username": "Akiscara_6484"
            }
          ]
        },
        "geo": {},
        "id": "2052635280197505368",
        "in_reply_to_user_id": "1634143760690057216",
        "lang": "en",
        "note_tweet": {
          "entities": {}
        },
        "possibly_sensitive": false,
        "public_metrics": {
          "bookmark_count": 0,
          "impression_count": 312,
          "like_count": 2,
          "quote_count": 0,
          "reply_count": 0,
          "retweet_count": 0
        },
        "referenced_tweets": [
          {
            "id": "2052437596438245439",
            "type": "replied_to"
          }
        ],
        "reply_settings": "everyone",
        "text": "@Akiscara_6484 Even if you just find yourself a hobby, like playing games, watching movies, or even dating, anything is fine. Just don't hurt yourself"
      }
    ],
    "users": [
      {
        "created_at": "2023-03-10T10:47:06.000Z",
        "derived": {
          "locations": [
            {
              "country_code": "JP",
              "full_name": "Ōsaka-shi, Ōsaka, Japan",
              "geo": {
                "coordinates": [
                  135.50218,
                  34.69374
                ],
                "type": "Point"
              },
              "locality": "Ōsaka-shi",
              "region": "Ōsaka"
            }
          ]
        },
        "description": "∥喵大王的极乐净土∥（18↓）\nod/自伤/碎碎念/双向/负能量/抽烟/坏小孩/抖m/受虐倾向/血腥/（喜欢cult片）/阴暗扭曲的爬行（家有男友）\n//@Akiscara_3405姐姐（本人脑子一根筋，听不懂你们说什么但会冒泡泡，见谅）",
        "entities": {
          "description": {
            "mentions": [
              {
                "end": 91,
                "start": 77,
                "username": "Akiscara_3405"
              }
            ]
          }
        },
        "id": "1634143760690057216",
        "location": "Kishiwada-shi, Osaka",
        "name": "喵大王",
        "pinned_tweet_id": "2043242409510007205",
        "profile_image_url": "https://pbs.twimg.com/profile_images/2044440756740653056/-JrtKJ53_normal.jpg",
        "protected": false,
        "public_metrics": {
          "followers_count": 399,
          "following_count": 131,
          "like_count": 6854,
          "listed_count": 0,
          "media_count": 213,
          "tweet_count": 2646
        },
        "username": "Akiscara_6484",
        "verified": false
      },
      {
        "created_at": "2026-03-24T15:25:33.000Z",
        "description": "Japanese learner，sub",
        "id": "2036464410286600192",
        "location": "Florida, USA",
        "name": "hanya",
        "profile_image_url": "https://pbs.twimg.com/profile_images/2052345724046864384/M9NXFXRL_normal.jpg",
        "protected": false,
        "public_metrics": {
          "followers_count": 9,
          "following_count": 212,
          "like_count": 3079,
          "listed_count": 0,
          "media_count": 1,
          "tweet_count": 292
        },
        "username": "hanya138884",
        "verified": false
      }
    ]
  }
}