{
  "data": {
    "article": {},
    "attachments": {},
    "author_id": "1634143760690057216",
    "conversation_id": "2059696255136415926",
    "created_at": "2026-05-28T08:54:57.000Z",
    "edit_controls": {
      "editable_until": "2026-05-28T09:54:57.000Z",
      "edits_remaining": 5,
      "is_edit_eligible": false
    },
    "edit_history_tweet_ids": [
      "2059921357761302891"
    ],
    "entities": {
      "mentions": [
        {
          "end": 12,
          "id": "2047554299815985152",
          "start": 0,
          "username": "fhrtdj47222"
        }
      ]
    },
    "geo": {},
    "id": "2059921357761302891",
    "in_reply_to_user_id": "2047554299815985152",
    "lang": "ja",
    "note_tweet": {
      "entities": {}
    },
    "possibly_sensitive": false,
    "public_metrics": {
      "bookmark_count": 0,
      "impression_count": 0,
      "like_count": 0,
      "quote_count": 0,
      "reply_count": 0,
      "retweet_count": 0
    },
    "referenced_tweets": [
      {
        "id": "2059907096884494505",
        "type": "replied_to"
      }
    ],
    "reply_settings": "everyone",
    "text": "@fhrtdj47222 我不知道"
  },
  "includes": {
    "tweets": [
      {
        "article": {},
        "attachments": {},
        "author_id": "1634143760690057216",
        "conversation_id": "2059696255136415926",
        "created_at": "2026-05-28T08:54:57.000Z",
        "edit_controls": {
          "editable_until": "2026-05-28T09:54:57.000Z",
          "edits_remaining": 5,
          "is_edit_eligible": false
        },
        "edit_history_tweet_ids": [
          "2059921357761302891"
        ],
        "entities": {
          "mentions": [
            {
              "end": 12,
              "id": "2047554299815985152",
              "start": 0,
              "username": "fhrtdj47222"
            }
          ]
        },
        "geo": {},
        "id": "2059921357761302891",
        "in_reply_to_user_id": "2047554299815985152",
        "lang": "ja",
        "note_tweet": {
          "entities": {}
        },
        "possibly_sensitive": false,
        "public_metrics": {
          "bookmark_count": 0,
          "impression_count": 0,
          "like_count": 0,
          "quote_count": 0,
          "reply_count": 0,
          "retweet_count": 0
        },
        "referenced_tweets": [
          {
            "id": "2059907096884494505",
            "type": "replied_to"
          }
        ],
        "reply_settings": "everyone",
        "text": "@fhrtdj47222 我不知道"
      },
      {
        "article": {},
        "attachments": {},
        "author_id": "2047554299815985152",
        "conversation_id": "2059696255136415926",
        "created_at": "2026-05-28T07:58:17.000Z",
        "edit_controls": {
          "editable_until": "2026-05-28T08:58:17.000Z",
          "edits_remaining": 5,
          "is_edit_eligible": false
        },
        "edit_history_tweet_ids": [
          "2059907096884494505"
        ],
        "entities": {
          "mentions": [
            {
              "end": 14,
              "id": "1634143760690057216",
              "start": 0,
              "username": "Akiscara_6484"
            }
          ]
        },
        "geo": {},
        "id": "2059907096884494505",
        "in_reply_to_user_id": "1634143760690057216",
        "lang": "zh",
        "note_tweet": {
          "entities": {}
        },
        "possibly_sensitive": false,
        "public_metrics": {
          "bookmark_count": 0,
          "impression_count": 3,
          "like_count": 0,
          "quote_count": 0,
          "reply_count": 1,
          "retweet_count": 0
        },
        "referenced_tweets": [
          {
            "id": "2059696255136415926",
            "type": "replied_to"
          }
        ],
        "reply_settings": "everyone",
        "text": "@Akiscara_6484 自己撸撸脚大拇指，裸手和隔手套那能一样吗，话说女人应该是无套比较爽吧"
      }
    ],
    "users": [
      {
        "created_at": "2023-03-10T10:47:06.000Z",
        "derived": {
          "locations": [
            {
              "country_code": "JP",
              "full_name": "Ōsaka-shi, Ōsaka, Japan",
              "geo": {
                "coordinates": [
                  135.50218,
                  34.69374
                ],
                "type": "Point"
              },
              "locality": "Ōsaka-shi",
              "region": "Ōsaka"
            }
          ]
        },
        "description": "∥喵大王的极乐净土∥（18↓）\nod/自伤/碎碎念/双向/负能量/抽烟/血腥/m/受虐（喜欢cult片）（家有男友）@Akiscara_3405姐姐（理解有问题）（戒药，戒割）不喜欢就请屏蔽我。门槛🚪60好友位，闲聊相互安慰，朋友圈开放。没礼貌的门槛🚪500  雷点：说我男朋友胖",
        "entities": {
          "description": {
            "mentions": [
              {
                "end": 72,
                "start": 58,
                "username": "Akiscara_3405"
              }
            ]
          }
        },
        "id": "1634143760690057216",
        "location": "Kishiwada-shi, Osaka",
        "name": "喵大王",
        "pinned_tweet_id": "2043242409510007205",
        "profile_image_url": "https://pbs.twimg.com/profile_images/2044440756740653056/-JrtKJ53_normal.jpg",
        "protected": false,
        "public_metrics": {
          "followers_count": 936,
          "following_count": 165,
          "like_count": 7037,
          "listed_count": 0,
          "media_count": 256,
          "tweet_count": 3945
        },
        "username": "Akiscara_6484",
        "verified": false
      },
      {
        "created_at": "2026-04-24T05:52:51.000Z",
        "description": "fuck that",
        "id": "2047554299815985152",
        "name": "仅我消逝的一面",
        "pinned_tweet_id": "2059432954800296327",
        "profile_image_url": "https://pbs.twimg.com/profile_images/2058089767259279360/ifUPu8vB_normal.jpg",
        "protected": false,
        "public_metrics": {
          "followers_count": 9,
          "following_count": 183,
          "like_count": 206,
          "listed_count": 0,
          "media_count": 12,
          "tweet_count": 118
        },
        "username": "fhrtdj47222",
        "verified": false
      }
    ]
  }
}