{
  "data": {
    "article": {},
    "attachments": {},
    "author_id": "1634143760690057216",
    "conversation_id": "2052433698927296672",
    "created_at": "2026-05-08T22:24:59.000Z",
    "edit_controls": {
      "editable_until": "2026-05-08T23:24:59.000Z",
      "edits_remaining": 5,
      "is_edit_eligible": false
    },
    "edit_history_tweet_ids": [
      "2052877452356256076"
    ],
    "entities": {
      "mentions": [
        {
          "end": 13,
          "id": "2018495751400140800",
          "start": 0,
          "username": "weak17747144"
        }
      ]
    },
    "geo": {},
    "id": "2052877452356256076",
    "in_reply_to_user_id": "2018495751400140800",
    "lang": "ja",
    "note_tweet": {
      "entities": {}
    },
    "possibly_sensitive": false,
    "public_metrics": {
      "bookmark_count": 0,
      "impression_count": 0,
      "like_count": 0,
      "quote_count": 0,
      "reply_count": 0,
      "retweet_count": 0
    },
    "referenced_tweets": [
      {
        "id": "2052614740996694323",
        "type": "replied_to"
      }
    ],
    "reply_settings": "everyone",
    "text": "@weak17747144 菌子锅"
  },
  "includes": {
    "tweets": [
      {
        "article": {},
        "attachments": {},
        "author_id": "1634143760690057216",
        "conversation_id": "2052433698927296672",
        "created_at": "2026-05-08T22:24:59.000Z",
        "edit_controls": {
          "editable_until": "2026-05-08T23:24:59.000Z",
          "edits_remaining": 5,
          "is_edit_eligible": false
        },
        "edit_history_tweet_ids": [
          "2052877452356256076"
        ],
        "entities": {
          "mentions": [
            {
              "end": 13,
              "id": "2018495751400140800",
              "start": 0,
              "username": "weak17747144"
            }
          ]
        },
        "geo": {},
        "id": "2052877452356256076",
        "in_reply_to_user_id": "2018495751400140800",
        "lang": "ja",
        "note_tweet": {
          "entities": {}
        },
        "possibly_sensitive": false,
        "public_metrics": {
          "bookmark_count": 0,
          "impression_count": 0,
          "like_count": 0,
          "quote_count": 0,
          "reply_count": 0,
          "retweet_count": 0
        },
        "referenced_tweets": [
          {
            "id": "2052614740996694323",
            "type": "replied_to"
          }
        ],
        "reply_settings": "everyone",
        "text": "@weak17747144 菌子锅"
      },
      {
        "article": {},
        "attachments": {},
        "author_id": "2018495751400140800",
        "conversation_id": "2052433698927296672",
        "created_at": "2026-05-08T05:01:04.000Z",
        "edit_controls": {
          "editable_until": "2026-05-08T06:01:04.000Z",
          "edits_remaining": 5,
          "is_edit_eligible": false
        },
        "edit_history_tweet_ids": [
          "2052614740996694323"
        ],
        "entities": {
          "mentions": [
            {
              "end": 14,
              "id": "1634143760690057216",
              "start": 0,
              "username": "Akiscara_6484"
            }
          ]
        },
        "geo": {},
        "id": "2052614740996694323",
        "in_reply_to_user_id": "1634143760690057216",
        "lang": "zh",
        "note_tweet": {
          "entities": {}
        },
        "possibly_sensitive": false,
        "public_metrics": {
          "bookmark_count": 0,
          "impression_count": 23,
          "like_count": 1,
          "quote_count": 0,
          "reply_count": 1,
          "retweet_count": 0
        },
        "referenced_tweets": [
          {
            "id": "2052433698927296672",
            "type": "replied_to"
          }
        ],
        "reply_settings": "everyone",
        "text": "@Akiscara_6484 啥都招了？告诉我今天吃了啥？😡😡😡"
      }
    ],
    "users": [
      {
        "created_at": "2023-03-10T10:47:06.000Z",
        "derived": {
          "locations": [
            {
              "country_code": "JP",
              "full_name": "Ōsaka-shi, Ōsaka, Japan",
              "geo": {
                "coordinates": [
                  135.50218,
                  34.69374
                ],
                "type": "Point"
              },
              "locality": "Ōsaka-shi",
              "region": "Ōsaka"
            }
          ]
        },
        "description": "∥喵大王的极乐净土∥（18↓）\nod/自伤/碎碎念/双向/负能量/抽烟/坏小孩/抖m/受虐倾向/血腥/（喜欢cult片）/阴暗扭曲的爬行（家有男友）\n//@Akiscara_3405姐姐（本人脑子一根筋，听不懂你们说什么但会冒泡泡，见谅）",
        "entities": {
          "description": {
            "mentions": [
              {
                "end": 91,
                "start": 77,
                "username": "Akiscara_3405"
              }
            ]
          }
        },
        "id": "1634143760690057216",
        "location": "Kishiwada-shi, Osaka",
        "name": "喵大王",
        "pinned_tweet_id": "2043242409510007205",
        "profile_image_url": "https://pbs.twimg.com/profile_images/2044440756740653056/-JrtKJ53_normal.jpg",
        "protected": false,
        "public_metrics": {
          "followers_count": 399,
          "following_count": 131,
          "like_count": 6854,
          "listed_count": 0,
          "media_count": 213,
          "tweet_count": 2656
        },
        "username": "Akiscara_6484",
        "verified": false
      },
      {
        "created_at": "2026-02-03T01:25:27.000Z",
        "description": "平民一个",
        "id": "2018495751400140800",
        "name": "weak177 weak177",
        "profile_image_url": "https://pbs.twimg.com/profile_images/2035560286334398464/ZAjIpgSW_normal.jpg",
        "protected": false,
        "public_metrics": {
          "followers_count": 0,
          "following_count": 73,
          "like_count": 89,
          "listed_count": 0,
          "media_count": 3,
          "tweet_count": 20
        },
        "username": "weak17747144",
        "verified": false
      }
    ]
  }
}